
[
    {
        "productId": 1,
        "img": "https://m.media-amazon.com/images/I/6125yAfsJKL._AC_UX575_.jpg",
        "title": "Nike Air Monarch IV",
        "description": "Step into classic style with the Nike Air Monarch IV. These iconic white sneakers from Nike provide comfort and versatility for your everyday activities.",
        "prevPrice": 140.00,
        "newPrice": 200.00,
        "company": "Nike",
        "color": "white",
        "category": "sneakers",
        "sale": false
    },
    {
        "productId": 2,
        "img": "https://m.media-amazon.com/images/I/519MRhRKGFL._AC_UX575_.jpg",
        "title": "Nike Air Vapormax Plus",
        "description": "Elevate your style with the Nike Air Vapormax Plus in striking red. These sneakers are designed for a bold and trendy look, making a statement wherever you go.",
        "prevPrice": 140.00,
        "newPrice": 200.00,
        "company": "Nike",
        "color": "red",
        "category": "sneakers",
        "sale": true
    },

    {
        "productId": 3,
        "img": "https://m.media-amazon.com/images/I/51+P9uAvb1L._AC_UY695_.jpg",
        "title": "Nike Waffle One Sneaker",
        "description": "Experience comfort and style with the Nike Waffle One Sneaker in vibrant green. Ideal for everyday wear, these sneakers provide a perfect blend of fashion and functionality.",
        "prevPrice": 140.00,
        "newPrice": 200.00,
        "company": "Nike",
        "color": "green",
        "category": "sneakers",
        "sale": false
    },
    {
        "productId": 4,
        "img": "https://m.media-amazon.com/images/I/71oEKkghg-L._AC_UX575_.jpg",
        "title": "Nike Running Shoe",
        "description": "Conquer your runs with the Nike Running Shoe in sleek black. These shoes from Adidas are designed for optimal performance and comfort during your daily runs and workouts.",
        "prevPrice": 140.00,
        "newPrice": 200.00,
        "company": "Adidas",
        "color": "black",
        "category": "sneakers",
        "sale": false
    },
    {
        "productId": 5,
        "img": "https://m.media-amazon.com/images/I/41M54ztS6IL._AC_SY625._SX._UX._SY._UY_.jpg",
        "title": "Flat Slip On Pumps",
        "description": "Step into style with these green Flat Slip On Pumps from Vans. Perfect for casual occasions, these pumps offer both comfort and fashion.",
        "prevPrice": 140.00,
        "newPrice": 200.00,
        "company": "Vans",
        "color": "green",
        "category": "flats",
        "sale": false
    },
    {
        "productId": 6,
        "img": "https://m.media-amazon.com/images/I/71zKuNICJAL._AC_UX625_.jpg",
        "title": "Knit Ballet Flat",
        "description": "Walk in elegance with the Knit Ballet Flat from Adidas in classic black. Ideal for both casual and semi-formal occasions, these flats offer style and comfort.",
        "prevPrice": 140.00,
        "newPrice": 50.00,
        "company": "Adidas",
        "color": "black",
        "category": "flats",
        "sale": false
    },

    {
        "productId": 7,
        "img": "https://m.media-amazon.com/images/I/61V9APfz97L._AC_UY695_.jpg",
        "title": "Loafer Flats",
        "description": "Step into comfort and style with Loafer Flats from Vans in pristine white. These flats are perfect for a casual yet sophisticated look.",
        "prevPrice": 140.00,
        "newPrice": 50.00,
        "company": "Vans",
        "color": "white",
        "category": "flats",
        "sale": true
    },

    {
        "productId": 8,
        "img": "https://m.media-amazon.com/images/I/71VaQ+V6XnL._AC_UY695_.jpg",
        "title": "Nike Zoom Freak",
        "description": "Unleash your athletic prowess with the Nike Zoom Freak in vibrant green. These sneakers from Nike are designed for high performance and a bold look.",
        "prevPrice": 140.00,
        "newPrice": 200.00,
        "company": "Nike",
        "color": "green",
        "category": "sneakers",
        "sale": false
    },

    {
        "productId": 9,
        "img": "https://m.media-amazon.com/images/I/61-cBsLhJHL._AC_UY695_.jpg",
        "title": "Nike Men's Sneaker",
        "description": "Step into style with the Nike Men's Sneaker in cool blue. These sneakers from Adidas combine fashion with comfort for a versatile footwear option.",
        "prevPrice": 140.00,
        "newPrice": 200.00,
        "company": "Adidas",
        "color": "blue",
        "category": "sneakers",
        "sale": false
    },

    {
        "productId": 10,
        "img": "https://m.media-amazon.com/images/I/81xXDjojYKS._AC_UX575_.jpg",
        "title": "PUMA BLACK-OCE",
        "description": "Dive into style with the PUMA BLACK-OCE sneakers in trendy green. These sneakers from Puma offer a perfect blend of fashion and comfort for your everyday adventures.",
        "prevPrice": 140.00,
        "newPrice": 150.00,
        "company": "Puma",
        "color": "green",
        "category": "sneakers",
        "sale": false
    },
    {
        "productId": 11,
        "img": "https://m.media-amazon.com/images/I/71E75yRwCDL._AC_UY575_.jpg",
        "title": "Pacer Future Sneaker",
        "description": "Step into the future of fashion with the Pacer Future Sneaker in bold red. These sneakers from Puma are designed for a stylish and comfortable stride.",
        "prevPrice": 140.00,
        "newPrice": 150.00,
        "company": "Puma",
        "color": "red",
        "category": "sneakers",
        "sale": false
    },
    {
        "productId": 12,
        "img": "https://m.media-amazon.com/images/I/71jeoX0rMBL._AC_UX575_.jpg",
        "title": "Unisex-Adult Super",
        "description": "Experience super comfort and style with the Unisex-Adult Super sneakers from Puma in classic black. These sneakers are perfect for casual and sporty occasions.",
        "prevPrice": 140.00,
        "newPrice": 150.00,
        "company": "Puma",
        "color": "black",
        "category": "sneakers",
        "sale": false
    },
    {
        "productId": 13,
        "img": "https://m.media-amazon.com/images/I/61TM6Q9dvxL._AC_UX575_.jpg",
        "title": "Roma Basic Sneaker",
        "description": "Step into the basics of fashion with the Roma Basic Sneaker in pristine white. These sneakers from Puma offer a clean and timeless style for your everyday look.",
        "prevPrice": 140.00,
        "newPrice": 150.00,
        "company": "Puma",
        "color": "white",
        "category": "sneakers",
        "sale": false
    },
    {
        "productId": 14,
        "img": "https://m.media-amazon.com/images/I/7128-af7joL._AC_UY575_.jpg",
        "title": "Pacer Future Doubleknit",
        "description": "Step into the future of fashion with the Pacer Future Doubleknit sneakers from Puma in sleek black. These sneakers are designed for a stylish and comfortable stride.",
        "prevPrice": 140.00,
        "newPrice": 150.00,
        "company": "Puma",
        "color": "black",
        "category": "sneakers",
        "sale": false
    },

    {
        "productId": 15,
        "img": "https://m.media-amazon.com/images/I/81xXDjojYKS._AC_UX575_.jpg",
        "title": "Fusion Evo Golf Shoe",
        "description": "Hit the greens in style with the Fusion Evo Golf Shoe from Puma in vibrant green. These golf shoes offer a perfect blend of fashion and functionality for your golfing adventures.",
        "prevPrice": 140.00,
        "newPrice": 100.00,
        "company": "Puma",
        "color": "green",
        "category": "sneakers",
        "sale": false
    },
    {
        "productId": 16,
        "img": "https://m.media-amazon.com/images/I/719gdz8lsTS._AC_UX575_.jpg",
        "title": "Rainbow Chex Skate",
        "description": "Skate in style with the Rainbow Chex Skate flats from Vans in bold red. These flats provide both comfort and fashion for your skateboarding sessions.",
        "prevPrice": 140.00,
        "newPrice": 100.00,
        "company": "Vans",
        "color": "red",
        "category": "flats",
        "sale": false
    },
    {
        "productId": 17,
        "img": "https://m.media-amazon.com/images/I/71gpFHJlnoL._AC_UX575_.jpg",
        "title": "Low-Top Trainers",
        "description": "Step into casual style with the Low-Top Trainers from Vans in classic white. These trainers are perfect for a laid-back and comfortable look.",
        "prevPrice": 140.00,
        "newPrice": 100.00,
        "company": "Vans",
        "color": "white",
        "category": "sandals",
        "sale": false
    },
    {
        "productId": 18,
        "img": "https://m.media-amazon.com/images/I/71pf7VFs9CL._AC_UX575_.jpg",
        "title": "Vans Unisex Low-Top",
        "description": "Experience versatile style with the Vans Unisex Low-Top sandals in cool blue. These sandals from Vans provide both comfort and fashion for your casual outings.",
        "prevPrice": 140.00,
        "newPrice": 100.00,
        "company": "Vans",
        "color": "blue",
        "category": "sandals",
        "sale": false
    },
    {
        "productId": 19,
        "img": "https://m.media-amazon.com/images/I/61N4GyWcHPL._AC_UY575_.jpg",
        "title": "Classic Bandana Sneakers",
        "description": "Step into classic style with the Classic Bandana Sneakers from Nike in bold black. These sneakers offer a timeless and trendy look for your everyday adventures.",
        "prevPrice": 140.00,
        "newPrice": 50.00,
        "company": "Nike",
        "color": "black",
        "category": "sandals",
        "sale": false
    },
    {
        "productId": 20,
        "img": "https://m.media-amazon.com/images/I/61bncQ44yML._AC_UX695_.jpg",
        "title": "Chunky High Heel",
        "description": "Elevate your style with the Chunky High Heel from Vans in classic black. These high heels are perfect for adding a touch of sophistication to your look.",
        "prevPrice": 140.00,
        "newPrice": 50.00,
        "company": "Vans",
        "color": "black",
        "category": "heels",
        "sale": true
    },
    {
        "productId": 21,
        "img": "https://m.media-amazon.com/images/I/71czu7WgGuL._AC_UY695_.jpg",
        "title": "Slip On Stiletto High Heel",
        "description": "Slip into elegance with the Slip On Stiletto High Heel from Puma in sleek black. These stiletto heels offer a combination of style and sophistication for your formal occasions.",
        "prevPrice": 140.00,
        "newPrice": 100.00,
        "company": "puma",
        "color": "black",
        "category": "heels",
        "sale": false
    },
    {
        "productId": 22,
        "img": "https://m.media-amazon.com/images/I/61men05KRxL._AC_UY625_.jpg",
        "title": "DREAM PAIRS Court Shoes",
        "description": "Step into elegance with the DREAM PAIRS Court Shoes from Nike in bold red. These court shoes offer a perfect blend of style and comfort for your formal events.",
        "prevPrice": 140.00,
        "newPrice": 150.00,
        "company": "Nike",
        "color": "red",
        "category": "heels",
        "sale": false
    },
    {
        "productId": 23,
        "img": "https://m.media-amazon.com/images/I/519MRhRKGFL._AC_UX575_.jpg",
        "title": "Nike Air Vapormax Plus",
        "description": "Elevate your style with the Nike Air Vapormax Plus in striking red. These sneakers are designed for a bold and trendy look, making a statement wherever you go.",
        "prevPrice": 140.00,
        "newPrice": 200.00,
        "company": "Nike",
        "color": "red",
        "category": "sneakers",
        "sale": false
    },
    {
        "productId": 24,
        "img": "https://m.media-amazon.com/images/I/51PGWTXgf-L._AC_UY625_.jpg",
        "title": "Low Mid Block Heels",
        "description": "Step into elegance with the Low Mid Block Heels from Nike in classic black. These heels offer a perfect blend of style and comfort for your formal occasions.",
        "prevPrice": 140.00,
        "newPrice": 200.00,
        "company": "Nike",
        "color": "black",
        "category": "heels",
        "sale": false
    },
    {
        "productId": 25,
        "img": "https://m.media-amazon.com/images/I/616sA5XUKtL._AC_UY675_.jpg",
        "title": "Chunky High Heel",
        "description": "Elevate your style with the Chunky High Heel from Adidas in classic black. These high heels are perfect for adding a touch of sophistication to your look.",
        "prevPrice": 140.00,
        "newPrice": 50.00,
        "company": "Adidas",
        "color": "black",
        "category": "heels",
        "sale": false
    },
    {
        "productId": 26,
        "img": "https://m.media-amazon.com/images/I/71h5+MbEK7L._AC_UY625_.jpg",
        "title": "Amore Fashion Stilettos",
        "description": "Step into elegance with the Amore Fashion Stilettos from Adidas in pristine white. These stiletto heels offer a combination of style and sophistication for your formal occasions.",
        "prevPrice": 140.00,
        "newPrice": 150.00,
        "company": "Adidas",
        "color": "white",
        "category": "heels",
        "sale": false
    },
    {
        "productId": 27,
        "img": "https://m.media-amazon.com/images/I/61uw5RDxKQL._AC_UY625_.jpg",
        "title": "Bridal Sandals Glitter",
        "description": "Walk down the aisle in style with the Bridal Sandals Glitter from Adidas in classic black. These sandals offer a touch of sparkle and elegance for your special day.",
        "prevPrice": 140.00,
        "newPrice": 50.00,
        "company": "Adidas",
        "color": "black",
        "category": "heels",
        "sale": false
    },
    {
        "productId": 28,
        "img": "https://m.media-amazon.com/images/I/71yhoZP0l6L._AC_UY695_.jpg",
        "title": "Wedding Prom Bridal",
        "description": "Step into elegance with the Wedding Prom Bridal flats from Adidas in classic black. These flats offer a comfortable and stylish option for your special occasions.",
        "prevPrice": 140.00,
        "newPrice": 50.00,
        "company": "Adidas",
        "color": "black",
        "category": "flats",
        "sale": false
    }
]

